whatthefuck.py
whatthefuck-1.2.dist-info/LICENSE
whatthefuck-1.2.dist-info/METADATA
whatthefuck-1.2.dist-info/WHEEL
whatthefuck-1.2.dist-info/top_level.txt
whatthefuck-1.2.dist-info/RECORD
