Metadata-Version: 2.1
Name: whatthefuck
Version: 1.2
Summary: Frustration made me develop this script.
Home-page: UNKNOWN
Author: Shubham Rath
Author-email: shubhamrath.iiitb@gmail.com
License: UNKNOWN
Platform: UNKNOWN
Classifier: Programming Language :: Python :: 3
Classifier: License :: OSI Approved :: MIT License
Classifier: Operating System :: OS Independent
Requires-Python: >=3.5
License-File: LICENSE
